CHANGELOG.rst
LICENSE
MANIFEST.in
README.rst
setup.cfg
setup.py
versioneer.py
openscm/__init__.py
openscm/_version.py
openscm/adapter.py
openscm/core.py
openscm/errors.py
openscm/openscm.py
openscm/parameter_views.py
openscm/parameters.py
openscm/regions.py
openscm/timeseries_converter.py
openscm/utils.py
openscm.egg-info/PKG-INFO
openscm.egg-info/SOURCES.txt
openscm.egg-info/dependency_links.txt
openscm.egg-info/requires.txt
openscm.egg-info/top_level.txt
openscm/adapters/__init__.py
openscm/scmdataframe/__init__.py
openscm/scmdataframe/base.py
openscm/scmdataframe/filters.py
openscm/scmdataframe/offsets.py
openscm/scmdataframe/parameter_type.py
openscm/scmdataframe/pyam_compat.py
openscm/scmdataframe/timeindex.py
openscm/units/__init__.py
openscm/units/metric_conversions.csv