Metadata-Version: 2.1
Name: openscm
Version: 0.1.0a0
Summary: A unifying interface for Simple Climate Models
Home-page: https://github.com/openclimatedata/openscm
Author: Robert Gieseke, Jared Lewis, Zeb Nicholls, Sven Willner
Author-email: robert.gieseke@pik-potsdam.de, jared.lewis@climate-energy-college.org, zebedee.nicholls@climate-energy-college.org, sven.willner@pik-potsdam.de
License: GNU Affero General Public License v3.0 or later
Project-URL: Bug Reports, https://github.com/openclimatedata/openscm/issues
Project-URL: Documentation, https://openscm.readthedocs.io/en/latest
Project-URL: Source, https://github.com/openclimatedata/openscm
Keywords: simple climate model
Platform: UNKNOWN
Classifier: Development Status :: 3 - Alpha
Classifier: Intended Audience :: Developers
Classifier: License :: OSI Approved :: GNU Affero General Public License v3 or later (AGPLv3+)
Classifier: Programming Language :: Python :: 3
Classifier: Programming Language :: Python :: 3.6
Classifier: Programming Language :: Python :: 3.7
Provides-Extra: deploy
Provides-Extra: notebooks
Provides-Extra: tests
Provides-Extra: dev
Provides-Extra: docs
